Workbook

Sheet Catalogo_Productos
A1: SKU | B1: Nombre | C1: Categoria | D1: Subcategoria | E1: Tier | F1: COGS_USD | G1: Elasticidad | H1: Precio_Base_USD | I1: Stock_Actual
A2: IRN-FUE-BAR-0001 | B2: IRONSIDE Cerakote 20kg [BETTER] | C2: Fuerza Libre | D2: Barras Olímpicas | E2: Better | F2: 46.2 | G2: -1.26 | H2: 73.16 | I2: 188
A3: IRN-FUE-BAR-0002 | B3: IRONSIDE Hard Chrome 20kg [BETTER] | C3: Fuerza Libre | D3: Barras Olímpicas | E3: Better | F3: 119.1 | G3: -1.68 | H3: 186.28 | I3: 169
A4: IRN-FUE-BAR-0003 | B4: IRONSIDE Women 15kg [GOOD] | C4: Fuerza Libre | D4: Barras Olímpicas | E4: Good | F4: 112.82 | G4: -1.76 | H4: 161.68 | I4: 222
A5: IRN-FUE-BAR-0004 | B5: IRONSIDE Trap Bar Hex [BETTER] | C5: Fuerza Libre | D5: Barras Olímpicas | E5: Better | F5: 63.56 | G5: -1.5 | H5: 101.17 | I5: 210
A6: IRN-FUE-BAR-0005 | B6: IRONSIDE EZ Curl Bar [GOOD] | C6: Fuerza Libre | D6: Barras Olímpicas | E6: Good | F6: 49.35 | G6: -2.25 | H6: 73.56 | I6: 201
A7: IRN-FUE-BAR-0006 | B7: IRONSIDE Shorty 10kg [GOOD] | C7: Fuerza Libre | D7: Barras Olímpicas | E7: Good | F7: 144.08 | G7: -1.77 | H7: 208.05 | I7: 241
A8: IRN-FUE-DIS-0007 | B8: IRONSIDE Hi-Temp Recycled 5kg [BETTER] | C8: Fuerza Libre | D8: Discos Bumper | E8: Better | F8: 97.59 | G8: -1.19 | H8: 154.6 | I8: 35
A9: IRN-FUE-DIS-0008 | B9: IRONSIDE Hi-Temp 10kg [BEST] | C9: Fuerza Libre | D9: Discos Bumper | E9: Best | F9: 67.03 | G9: -1.07 | H9: 127.93 | I9: 105
A10: IRN-FUE-DIS-0009 | B10: IRONSIDE Hi-Temp 15kg [GOOD] | C10: Fuerza Libre | D10: Discos Bumper | E10: Good | F10: 112.11 | G10: -2.51 | H10: 167.2 | I10: 201
A11: IRN-FUE-DIS-0010 | B11: IRONSIDE Hi-Temp 20kg [BETTER] | C11: Fuerza Libre | D11: Discos Bumper | E11: Better | F11: 44.46 | G11: -1.19 | H11: 73.5 | I11: 98
A12: IRN-FUE-DIS-0011 | B12: IRONSIDE Hi-Temp 25kg [BETTER] | C12: Fuerza Libre | D12: Discos Bumper | E12: Better | F12: 39.46 | G12: -1.15 | H12: 63.03 | I12: 69
A13: IRN-FUE-DIS-0012 | B13: IRONSIDE Competition Urethane 10kg [BETTER] | C13: Fuerza Libre | D13: Discos Bumper | E13: Better | F13: 99.22 | G13: -1.42 | H13: 161.22 | I13: 179
... A351: IRN-RAC-BAN-0350 | B351: IRONSIDE Adjustable Incline/Decline FID Bench [BETTER] | C351: Racks & Estructuras | D351: Bancos | E351: Better | F351: 264.51 | G351: -1.4 | H351: 443.63 | I351: 187

Sheet Simulador_Pricing
A1: SKU | B1: Canal | C1: Moneda | D1: Precio Lista ($) | E1: % Descuento | F1: COGS ($) [VLOOKUP] | G1: Fee Canal (%) | H1: Precio Neto ($) | I1: Margen Unit ($) | J1: % Margen | K1: Vol. Base | L1: Elasticidad [VLOOKUP] | M1: Lift Equilibrio (%) | N1: Lift Esperado (%) | O1: Vol. Proyectado | P1: Revenue Proyectado ($) | Q1: Ganancia Proyectada ($) | R1: Ganancia Base ($) | S1: Ganancia Incremental ($) | T1: Dictamen Financiero
A2: IRN-FUE-BAR-0001 | B2: D2C_SHOPIFY | C2: USD | D2: 73.16 | E2: 0.1 | F2: =VLOOKUP(A2, Catalogo_Productos!$A$2:$I$351, 6, FALSE) | G2: =IF(B2="MELI_FULL", 0.14, IF(B2="D2C_SHOPIFY", 0.025, 0.01)) | H2: =D2*(1-E2) | I2: =H2-F2-(D2*G2) | J2: =I2/H2 | K2: 120 | L2: =VLOOKUP(A2, Catalogo_Productos!$A$2:$I$351, 7, FALSE) | M2: =IF(E2>=J2, 9.99, E2/(J2-E2)) | N2: =ABS(L2)*E2 | O2: =ROUND(K2*(1+N2), 0) | P2: =H2*O2 | Q2: =I2*O2 | R2: =(D2-F2-(D2*G2))*K2 | S2: =Q2-R2 | T2: =IF(S2>0, "APROBADA", "RECHAZADA")
A3: IRN-FUE-BAR-0002 | B3: MELI_FULL | C3: USD | D3: 186.28 | E3: 0.15 | F3: =VLOOKUP(A3, Catalogo_Productos!$A$2:$I$351, 6, FALSE) | G3: =IF(B3="MELI_FULL", 0.14, IF(B3="D2C_SHOPIFY", 0.025, 0.01)) | H3: =D3*(1-E3) | I3: =H3-F3-(D3*G3) | J3: =I3/H3 | K3: 80 | L3: =VLOOKUP(A3, Catalogo_Productos!$A$2:$I$351, 7, FALSE) | M3: =IF(E3>=J3, 9.99, E3/(J3-E3)) | N3: =ABS(L3)*E3 | O3: =ROUND(K3*(1+N3), 0) | P3: =H3*O3 | Q3: =I3*O3 | R3: =(D3-F3-(D3*G3))*K3 | S3: =Q3-R3 | T3: =IF(S3>0, "APROBADA", "RECHAZADA")
A4: IRN-FUE-BAR-0003 | B4: D2C_SHOPIFY | C4: USD | D4: 161.68 | E4: 0.1 | F4: =VLOOKUP(A4, Catalogo_Productos!$A$2:$I$351, 6, FALSE) | G4: =IF(B4="MELI_FULL", 0.14, IF(B4="D2C_SHOPIFY", 0.025, 0.01)) | H4: =D4*(1-E4) | I4: =H4-F4-(D4*G4) | J4: =I4/H4 | K4: 120 | L4: =VLOOKUP(A4, Catalogo_Productos!$A$2:$I$351, 7, FALSE) | M4: =IF(E4>=J4, 9.99, E4/(J4-E4)) | N4: =ABS(L4)*E4 | O4: =ROUND(K4*(1+N4), 0) | P4: =H4*O4 | Q4: =I4*O4 | R4: =(D4-F4-(D4*G4))*K4 | S4: =Q4-R4 | T4: =IF(S4>0, "APROBADA", "RECHAZADA")
A5: IRN-FUE-BAR-0004 | B5: MELI_FULL | C5: USD | D5: 101.17 | E5: 0.2 | F5: =VLOOKUP(A5, Catalogo_Productos!$A$2:$I$351, 6, FALSE) | G5: =IF(B5="MELI_FULL", 0.14, IF(B5="D2C_SHOPIFY", 0.025, 0.01)) | H5: =D5*(1-E5) | I5: =H5-F5-(D5*G5) | J5: =I5/H5 | K5: 80 | L5: =VLOOKUP(A5, Catalogo_Productos!$A$2:$I$351, 7, FALSE) | M5: =IF(E5>=J5, 9.99, E5/(J5-E5)) | N5: =ABS(L5)*E5 | O5: =ROUND(K5*(1+N5), 0) | P5: =H5*O5 | Q5: =I5*O5 | R5: =(D5-F5-(D5*G5))*K5 | S5: =Q5-R5 | T5: =IF(S5>0, "APROBADA", "RECHAZADA")
A6: IRN-FUE-BAR-0005 | B6: D2C_SHOPIFY | C6: USD | D6: 73.56 | E6: 0.15 | F6: =VLOOKUP(A6, Catalogo_Productos!$A$2:$I$351, 6, FALSE) | G6: =IF(B6="MELI_FULL", 0.14, IF(B6="D2C_SHOPIFY", 0.025, 0.01)) | H6: =D6*(1-E6) | I6: =H6-F6-(D6*G6) | J6: =I6/H6 | K6: 120 | L6: =VLOOKUP(A6, Catalogo_Productos!$A$2:$I$351, 7, FALSE) | M6: =IF(E6>=J6, 9.99, E6/(J6-E6)) | N6: =ABS(L6)*E6 | O6: =ROUND(K6*(1+N6), 0) | P6: =H6*O6 | Q6: =I6*O6 | R6: =(D6-F6-(D6*G6))*K6 | S6: =Q6-R6 | T6: =IF(S6>0, "APROBADA", "RECHAZADA")
A7: IRN-FUE-BAR-0006 | B7: MELI_FULL | C7: USD | D7: 208.05 | E7: 0.1 | F7: =VLOOKUP(A7, Catalogo_Productos!$A$2:$I$351, 6, FALSE) | G7: =IF(B7="MELI_FULL", 0.14, IF(B7="D2C_SHOPIFY", 0.025, 0.01)) | H7: =D7*(1-E7) | I7: =H7-F7-(D7*G7) | J7: =I7/H7 | K7: 80 | L7: =VLOOKUP(A7, Catalogo_Productos!$A$2:$I$351, 7, FALSE) | M7: =IF(E7>=J7, 9.99, E7/(J7-E7)) | N7: =ABS(L7)*E7 | O7: =ROUND(K7*(1+N7), 0) | P7: =H7*O7 | Q7: =I7*O7 | R7: =(D7-F7-(D7*G7))*K7 | S7: =Q7-R7 | T7: =IF(S7>0, "APROBADA", "RECHAZADA")
A8: IRN-FUE-DIS-0007 | B8: D2C_SHOPIFY | C8: USD | D8: 154.6 | E8: 0.1 | F8: =VLOOKUP(A8, Catalogo_Productos!$A$2:$I$351, 6, FALSE) | G8: =IF(B8="MELI_FULL", 0.14, IF(B8="D2C_SHOPIFY", 0.025, 0.01)) | H8: =D8*(1-E8) | I8: =H8-F8-(D8*G8) | J8: =I8/H8 | K8: 120 | L8: =VLOOKUP(A8, Catalogo_Productos!$A$2:$I$351, 7, FALSE) | M8: =IF(E8>=J8, 9.99, E8/(J8-E8)) | N8: =ABS(L8)*E8 | O8: =ROUND(K8*(1+N8), 0) | P8: =H8*O8 | Q8: =I8*O8 | R8: =(D8-F8-(D8*G8))*K8 | S8: =Q8-R8 | T8: =IF(S8>0, "APROBADA", "RECHAZADA")
A9: IRN-FUE-DIS-0008 | B9: MELI_FULL | C9: USD | D9: 127.93 | E9: 0.15 | F9: =VLOOKUP(A9, Catalogo_Productos!$A$2:$I$351, 6, FALSE) | G9: =IF(B9="MELI_FULL", 0.14, IF(B9="D2C_SHOPIFY", 0.025, 0.01)) | H9: =D9*(1-E9) | I9: =H9-F9-(D9*G9) | J9: =I9/H9 | K9: 80 | L9: =VLOOKUP(A9, Catalogo_Productos!$A$2:$I$351, 7, FALSE) | M9: =IF(E9>=J9, 9.99, E9/(J9-E9)) | N9: =ABS(L9)*E9 | O9: =ROUND(K9*(1+N9), 0) | P9: =H9*O9 | Q9: =I9*O9 | R9: =(D9-F9-(D9*G9))*K9 | S9: =Q9-R9 | T9: =IF(S9>0, "APROBADA", "RECHAZADA")
A10: IRN-FUE-DIS-0009 | B10: D2C_SHOPIFY | C10: USD | D10: 167.2 | E10: 0.2 | F10: =VLOOKUP(A10, Catalogo_Productos!$A$2:$I$351, 6, FALSE) | G10: =IF(B10="MELI_FULL", 0.14, IF(B10="D2C_SHOPIFY", 0.025, 0.01)) | H10: =D10*(1-E10) | I10: =H10-F10-(D10*G10) | J10: =I10/H10 | K10: 120 | L10: =VLOOKUP(A10, Catalogo_Productos!$A$2:$I$351, 7, FALSE) | M10: =IF(E10>=J10, 9.99, E10/(J10-E10)) | N10: =ABS(L10)*E10 | O10: =ROUND(K10*(1+N10), 0) | P10: =H10*O10 | Q10: =I10*O10 | R10: =(D10-F10-(D10*G10))*K10 | S10: =Q10-R10 | T10: =IF(S10>0, "APROBADA", "RECHAZADA")
A11: IRN-FUE-DIS-0010 | B11: MELI_FULL | C11: USD | D11: 73.5 | E11: 0.1 | F11: =VLOOKUP(A11, Catalogo_Productos!$A$2:$I$351, 6, FALSE) | G11: =IF(B11="MELI_FULL", 0.14, IF(B11="D2C_SHOPIFY", 0.025, 0.01)) | H11: =D11*(1-E11) | I11: =H11-F11-(D11*G11) | J11: =I11/H11 | K11: 80 | L11: =VLOOKUP(A11, Catalogo_Productos!$A$2:$I$351, 7, FALSE) | M11: =IF(E11>=J11, 9.99, E11/(J11-E11)) | N11: =ABS(L11)*E11 | O11: =ROUND(K11*(1+N11), 0) | P11: =H11*O11 | Q11: =I11*O11 | R11: =(D11-F11-(D11*G11))*K11 | S11: =Q11-R11 | T11: =IF(S11>0, "APROBADA", "RECHAZADA")
A12: IRN-FUE-DIS-0011 | B12: D2C_SHOPIFY | C12: USD | D12: 63.03 | E12: 0.15 | F12: =VLOOKUP(A12, Catalogo_Productos!$A$2:$I$351, 6, FALSE) | G12: =IF(B12="MELI_FULL", 0.14, IF(B12="D2C_SHOPIFY", 0.025, 0.01)) | H12: =D12*(1-E12) | I12: =H12-F12-(D12*G12) | J12: =I12/H12 | K12: 120 | L12: =VLOOKUP(A12, Catalogo_Productos!$A$2:$I$351, 7, FALSE) | M12: =IF(E12>=J12, 9.99, E12/(J12-E12)) | N12: =ABS(L12)*E12 | O12: =ROUND(K12*(1+N12), 0) | P12: =H12*O12 | Q12: =I12*O12 | R12: =(D12-F12-(D12*G12))*K12 | S12: =Q12-R12 | T12: =IF(S12>0, "APROBADA", "RECHAZADA")
A13: IRN-FUE-DIS-0012 | B13: MELI_FULL | C13: USD | D13: 161.22 | E13: 0.1 | F13: =VLOOKUP(A13, Catalogo_Productos!$A$2:$I$351, 6, FALSE) | G13: =IF(B13="MELI_FULL", 0.14, IF(B13="D2C_SHOPIFY", 0.025, 0.01)) | H13: =D13*(1-E13) | I13: =H13-F13-(D13*G13) | J13: =I13/H13 | K13: 80 | L13: =VLOOKUP(A13, Catalogo_Productos!$A$2:$I$351, 7, FALSE) | M13: =IF(E13>=J13, 9.99, E13/(J13-E13)) | N13: =ABS(L13)*E13 | O13: =ROUND(K13*(1+N13), 0) | P13: =H13*O13 | Q13: =I13*O13 | R13: =(D13-F13-(D13*G13))*K13 | S13: =Q13-R13 | T13: =IF(S13>0, "APROBADA", "RECHAZADA")
... A41: IRN-RAC-BAN-0040 | B41: MELI_FULL | C41: USD | D41: 172.72 | E41: 0.1 | F41: =VLOOKUP(A41, Catalogo_Productos!$A$2:$I$351, 6, FALSE) | G41: =IF(B41="MELI_FULL", 0.14, IF(B41="D2C_SHOPIFY", 0.025, 0.01)) | H41: =D41*(1-E41) | I41: =H41-F41-(D41*G41) | J41: =I41/H41 | K41: 80 | L41: =VLOOKUP(A41, Catalogo_Productos!$A$2:$I$351, 7, FALSE) | M41: =IF(E41>=J41, 9.99, E41/(J41-E41)) | N41: =ABS(L41)*E41 | O41: =ROUND(K41*(1+N41), 0) | P41: =H41*O41 | Q41: =I41*O41 | R41: =(D41-F41-(D41*G41))*K41 | S41: =Q41-R41 | T41: =IF(S41>0, "APROBADA", "RECHAZADA")

Sheet Resumen_Ejecutivo_PL
A1: PANEL DE CONTROL FINANCIERO - IMPACTO EN P&L
A3: Métrica Clave de Campaña | B3: Fórmula Encadenada / Valor
A4: Revenue Proyectado de Campaña ($) | B4: =SUM(Simulador_Pricing!P2:P41)
A5: Ganancia Bruta Proyectada ($) | B5: =SUM(Simulador_Pricing!Q2:Q41)
A6: Ganancia Bruta Línea Base ($) | B6: =SUM(Simulador_Pricing!R2:R41)
A7: Ganancia Incremental Neta ($) | B7: =B3-B4
A8: Margen Bruto Ponderado Campaña (%) | B8: =B3/B2
A9: Promociones Aprobadas | B9: =COUNTIF(Simulador_Pricing!T2:T41, "APROBADA")
A10: Promociones Rechazadas (Veto Margen) | B10: =COUNTIF(Simulador_Pricing!T2:T41, "RECHAZADA")
A11: Tasa de Aprobación de Campaña (%) | B11: =B7/(B7+B8)

Sheet Benchmark_Competitivo
A1: SKU | B1: Competidor | C1: País | D1: Precio Nuestro (USD) | E1: Precio Competidor (USD) | F1: Price Index (%) | G1: Posicionamiento
A2: IRN-FUE-BAR-0001 | B2: SDmed | C2: CL | D2: 73.16 | E2: 63.23 | F2: =(D2/E2)*100 | G2: =IF(F2>115, "Overpriced", IF(F2>=105, "Healthy Premium", IF(F2>=95, "Competitive Parity", "Underpriced")))
A3: IRN-FUE-BAR-0001 | B3: SDmed | C3: MX | D3: 73.16 | E3: 63.23 | F3: =(D3/E3)*100 | G3: =IF(F3>115, "Overpriced", IF(F3>=105, "Healthy Premium", IF(F3>=95, "Competitive Parity", "Underpriced")))
A4: IRN-FUE-BAR-0001 | B4: SDmed | C4: AR | D4: 73.16 | E4: 63.23 | F4: =(D4/E4)*100 | G4: =IF(F4>115, "Overpriced", IF(F4>=105, "Healthy Premium", IF(F4>=95, "Competitive Parity", "Underpriced")))
A5: IRN-FUE-BAR-0001 | B5: Spartan | C5: CL | D5: 73.16 | E5: 73.33 | F5: =(D5/E5)*100 | G5: =IF(F5>115, "Overpriced", IF(F5>=105, "Healthy Premium", IF(F5>=95, "Competitive Parity", "Underpriced")))
A6: IRN-FUE-BAR-0001 | B6: Spartan | C6: MX | D6: 73.16 | E6: 73.33 | F6: =(D6/E6)*100 | G6: =IF(F6>115, "Overpriced", IF(F6>=105, "Healthy Premium", IF(F6>=95, "Competitive Parity", "Underpriced")))
A7: IRN-FUE-BAR-0001 | B7: Spartan | C7: AR | D7: 73.16 | E7: 73.33 | F7: =(D7/E7)*100 | G7: =IF(F7>115, "Overpriced", IF(F7>=105, "Healthy Premium", IF(F7>=95, "Competitive Parity", "Underpriced")))
A8: IRN-FUE-BAR-0001 | B8: Rogue | C8: CL | D8: 73.16 | E8: 92.48 | F8: =(D8/E8)*100 | G8: =IF(F8>115, "Overpriced", IF(F8>=105, "Healthy Premium", IF(F8>=95, "Competitive Parity", "Underpriced")))
A9: IRN-FUE-BAR-0001 | B9: Rogue | C9: MX | D9: 73.16 | E9: 92.48 | F9: =(D9/E9)*100 | G9: =IF(F9>115, "Overpriced", IF(F9>=105, "Healthy Premium", IF(F9>=95, "Competitive Parity", "Underpriced")))
A10: IRN-FUE-BAR-0001 | B10: Rogue | C10: AR | D10: 73.16 | E10: 92.48 | F10: =(D10/E10)*100 | G10: =IF(F10>115, "Overpriced", IF(F10>=105, "Healthy Premium", IF(F10>=95, "Competitive Parity", "Underpriced")))
A11: IRN-FUE-BAR-0001 | B11: Tayga | C11: CL | D11: 73.16 | E11: 69.55 | F11: =(D11/E11)*100 | G11: =IF(F11>115, "Overpriced", IF(F11>=105, "Healthy Premium", IF(F11>=95, "Competitive Parity", "Underpriced")))
A12: IRN-FUE-BAR-0001 | B12: Tayga | C12: MX | D12: 73.16 | E12: 69.55 | F12: =(D12/E12)*100 | G12: =IF(F12>115, "Overpriced", IF(F12>=105, "Healthy Premium", IF(F12>=95, "Competitive Parity", "Underpriced")))
A13: IRN-FUE-BAR-0001 | B13: Tayga | C13: AR | D13: 73.16 | E13: 69.55 | F13: =(D13/E13)*100 | G13: =IF(F13>115, "Overpriced", IF(F13>=105, "Healthy Premium", IF(F13>=95, "Competitive Parity", "Underpriced")))
... A101: IRN-FUE-DIS-0012 | B101: Spartan | C101: CL | D101: 161.22 | E101: 162.81 | F101: =(D101/E101)*100 | G101: =IF(F101>115, "Overpriced", IF(F101>=105, "Healthy Premium", IF(F101>=95, "Competitive Parity", "Underpriced")))
